colorFinder/__init__.py
colorFinder/colorFinder.py
colorFinder-1.0.2.dist-info/LICENSE.txt
colorFinder-1.0.2.dist-info/METADATA
colorFinder-1.0.2.dist-info/WHEEL
colorFinder-1.0.2.dist-info/top_level.txt
colorFinder-1.0.2.dist-info/RECORD
