Metadata-Version: 2.1
Name: colorFinder
Version: 1.0.2
Summary: A package for automatically finding the most common used colors in an image.
Home-page: https://github.com/danysrour/imageColorFinder
Author: Dany Srour
Author-email: dany.srour@gmail.com
Classifier: Development Status :: 5 - Production/Stable
Classifier: Intended Audience :: Developers
Classifier: License :: OSI Approved :: MIT License
Classifier: Programming Language :: Python :: 3
Classifier: Programming Language :: Python :: 3.6
Classifier: Programming Language :: Python :: 3.7
Classifier: Programming Language :: Python :: 3.8
Classifier: Programming Language :: Python :: 3.9
Requires-Python: >=3.6
License-File: LICENSE.txt
Requires-Dist: Pillow
Requires-Dist: requests
